[
	{
		"0": [
			{
				"x": "23.820792",
				"y": "89.840611"
			},
			{
				"x": "24",
				"y": "90"
			},
			{
				"x": "24.179208",
				"y": "90.159389"
			},
			{
				"x": "24.358416",
				"y": "90.318778"
			},
			{
				"x": "24.537624",
				"y": "90.478167"
			},
			{
				"x": "24.716832",
				"y": "90.637556"
			},
			{
				"x": "24.89604",
				"y": "90.796945"
			},
			{
				"x": "25.075248",
				"y": "90.956334"
			},
			{
				"x": "25.254456",
				"y": "91.115723"
			},
			{
				"x": "25.433664",
				"y": "91.275112"
			}
		]
	},
	{
		"1": [
			{
				"x": "24.109419",
				"y": "89.416264"
			},
			{
				"x": "24.2",
				"y": "89.5"
			},
			{
				"x": "24.290581",
				"y": "89.583736"
			},
			{
				"x": "24.381162",
				"y": "89.667472"
			},
			{
				"x": "24.471743",
				"y": "89.751208"
			},
			{
				"x": "24.562324",
				"y": "89.834944"
			},
			{
				"x": "24.652905",
				"y": "89.91868"
			},
			{
				"x": "24.743486",
				"y": "90.002416"
			},
			{
				"x": "24.834067",
				"y": "90.086152"
			},
			{
				"x": "24.924648",
				"y": "90.169888"
			}
		]
	},
	{
		"2": [
			{
				"undefined": "2",
				"x": "23.780584",
				"y": "90.462712"
			},
			{
				"x": "23.9",
				"y": "90.6"
			},
			{
				"x": "24.019416",
				"y": "90.737288"
			},
			{
				"x": "24.138832",
				"y": "90.874576"
			},
			{
				"x": "24.258248",
				"y": "91.011864"
			},
			{
				"x": "24.377664",
				"y": "91.149152"
			},
			{
				"x": "24.49708",
				"y": "91.28644"
			},
			{
				"x": "24.616496",
				"y": "91.423728"
			},
			{
				"x": "24.735912",
				"y": "91.561016"
			},
			{
				"x": "24.855328",
				"y": "91.698304"
			}
		]
	}
]
